{
  "synced_at": "2026-04-19T18:30:19.572958+00:00",
  "activity": {
    "id": "i135149572",
    "start_date_local": "2025-05-25T10:05:38",
    "type": "Run",
    "icu_ignore_time": false,
    "icu_pm_cp": null,
    "icu_pm_w_prime": null,
    "icu_pm_p_max": null,
    "icu_pm_ftp": null,
    "icu_pm_ftp_secs": null,
    "icu_pm_ftp_watts": null,
    "icu_ignore_power": false,
    "icu_rolling_cp": null,
    "icu_rolling_w_prime": null,
    "icu_rolling_p_max": null,
    "icu_rolling_ftp": null,
    "icu_rolling_ftp_delta": null,
    "icu_training_load": 81,
    "icu_atl": 58.326084,
    "icu_ctl": 50.57644,
    "ss_p_max": null,
    "ss_w_prime": null,
    "ss_cp": null,
    "paired_event_id": null,
    "icu_ftp": null,
    "icu_joules": null,
    "icu_recording_time": 5097,
    "elapsed_time": 5635,
    "icu_weighted_avg_watts": null,
    "carbs_used": null,
    "name": "Stockholm Running",
    "description": null,
    "start_date": "2025-05-25T08:05:38Z",
    "distance": 15579.83,
    "icu_distance": 15579.83,
    "moving_time": 5039,
    "coasting_time": 24,
    "total_elevation_gain": 119.897835,
    "total_elevation_loss": 117.39717,
    "timezone": null,
    "trainer": null,
    "sub_type": null,
    "commute": false,
    "race": false,
    "max_speed": 4.264,
    "average_speed": 3.082,
    "device_watts": true,
    "has_heartrate": true,
    "max_heartrate": 173,
    "average_heartrate": 149,
    "average_cadence": 84.15234,
    "calories": 1099,
    "average_temp": 22.608885,
    "min_temp": 20,
    "max_temp": 26,
    "avg_lr_balance": null,
    "gap": 3.0954838,
    "gap_model": "STRAVA_RUN",
    "use_elevation_correction": true,
    "gear": null,
    "perceived_exertion": null,
    "device_name": "Garmin Forerunner 265",
    "power_meter": null,
    "power_meter_serial": null,
    "power_meter_battery": null,
    "crank_length": null,
    "external_id": "19228340766",
    "file_sport_index": 0,
    "file_type": "fit",
    "icu_athlete_id": "i540405",
    "created": "2026-03-27T13:51:33.800+00:00",
    "icu_sync_date": "2026-03-27T13:51:52.947+00:00",
    "analyzed": "2026-03-27T13:51:52.947+00:00",
    "icu_w_prime": null,
    "p_max": null,
    "threshold_pace": null,
    "icu_hr_zones": [
      147,
      156,
      165,
      174,
      179,
      184,
      193
    ],
    "pace_zones": null,
    "lthr": 175,
    "icu_resting_hr": 50,
    "icu_weight": 69.0,
    "icu_power_zones": null,
    "icu_sweet_spot_min": 0,
    "icu_sweet_spot_max": 0,
    "icu_power_spike_threshold": null,
    "trimp": 140.58852,
    "icu_warmup_time": 300,
    "icu_cooldown_time": 300,
    "icu_chat_id": null,
    "icu_ignore_hr": false,
    "ignore_velocity": false,
    "ignore_pace": false,
    "ignore_parts": null,
    "icu_training_load_data": 100,
    "interval_summary": [
      "12x 5m24s 152bpm",
      "2x 6m30s 139bpm",
      "1x 12m59s 126bpm",
      "1x 3m12s 153bpm"
    ],
    "skyline_chart_bytes": "CAcSHrsCiAXFAsUCxwLBAssCxAK6AtUCywLPAsMCxAK1ARoPT1RWVU5UXl5eSFBTUlZXIg8BAQICAQEDBAMBAQEBAgIoAg==",
    "stream_types": [
      "time",
      "watts",
      "cadence",
      "heartrate",
      "distance",
      "altitude",
      "latlng",
      "velocity_smooth",
      "temp",
      "torque",
      "fixed_altitude"
    ],
    "has_weather": false,
    "has_segments": false,
    "power_field_names": [
      "power"
    ],
    "power_field": "power",
    "icu_zone_times": null,
    "icu_hr_zone_times": [
      2367,
      1366,
      563,
      741,
      0,
      0,
      0
    ],
    "pace_zone_times": null,
    "gap_zone_times": null,
    "use_gap_zone_times": true,
    "custom_zones": null,
    "tiz_order": "POWER_HR_PACE",
    "polarization_index": 0.0,
    "icu_achievements": null,
    "icu_intervals_edited": null,
    "lock_intervals": null,
    "icu_lap_count": 16,
    "icu_joules_above_ftp": null,
    "icu_max_wbal_depletion": null,
    "icu_hrr": null,
    "icu_sync_error": null,
    "icu_color": null,
    "icu_power_hr_z2": null,
    "icu_power_hr_z2_mins": null,
    "icu_cadence_z2": null,
    "icu_rpe": 4,
    "feel": 1,
    "kg_lifted": null,
    "decoupling": null,
    "icu_median_time_delta": 1,
    "p30s_exponent": null,
    "workout_shift_secs": null,
    "strava_id": null,
    "lengths": null,
    "pool_length": null,
    "compliance": null,
    "coach_tick": null,
    "source": "GARMIN_CONNECT",
    "oauth_client_id": null,
    "oauth_client_name": null,
    "average_altitude": 20.69536,
    "min_altitude": 6.0509577,
    "max_altitude": 40.948494,
    "power_load": null,
    "hr_load": 81,
    "pace_load": null,
    "hr_load_type": "HRSS",
    "pace_load_type": null,
    "tags": null,
    "attachments": null,
    "recording_stops": [
      1805,
      1903,
      2461,
      3351,
      4005,
      4155,
      4269,
      5495
    ],
    "average_weather_temp": null,
    "min_weather_temp": null,
    "max_weather_temp": null,
    "average_feels_like": null,
    "min_feels_like": null,
    "max_feels_like": null,
    "average_wind_speed": null,
    "average_wind_gust": null,
    "prevailing_wind_deg": null,
    "headwind_percent": null,
    "tailwind_percent": null,
    "average_clouds": null,
    "max_rain": null,
    "max_snow": null,
    "carbs_ingested": null,
    "route_id": null,
    "pace": 3.0918496,
    "athlete_max_hr": 193,
    "group": "a2a92728",
    "icu_intensity": 75.637375,
    "icu_efficiency_factor": null,
    "icu_power_hr": null,
    "session_rpe": 335,
    "average_stride": 1.102233,
    "icu_average_watts": null,
    "icu_variability_index": null,
    "strain_score": null
  },
  "laps": {
    "id": "i135149572",
    "analyzed": "2026-03-27T13:51:52.947+00:00",
    "icu_intervals": [
      {
        "start_index": 0,
        "distance": 1004.61,
        "moving_time": 315,
        "elapsed_time": 315,
        "average_watts": null,
        "average_watts_alt": null,
        "average_watts_alt_acc": null,
        "min_watts": null,
        "max_watts": null,
        "average_watts_kg": null,
        "max_watts_kg": null,
        "intensity": 79,
        "w5s_variability": null,
        "weighted_average_watts": null,
        "training_load": null,
        "joules": null,
        "joules_above_ftp": null,
        "decoupling": null,
        "avg_lr_balance": null,
        "average_dfa_a1": null,
        "average_epoc": null,
        "wbal_start": null,
        "wbal_end": null,
        "average_respiration": null,
        "average_tidal_volume": null,
        "average_tidal_volume_min": null,
        "zone": 1,
        "zone_min_watts": null,
        "zone_max_watts": null,
        "average_speed": 3.189238,
        "min_speed": 0.0,
        "max_speed": 4.264,
        "gap": 3.0902154,
        "average_heartrate": 139,
        "min_heartrate": 83,
        "max_heartrate": 152,
        "average_cadence": 83.542854,
        "min_cadence": 0,
        "max_cadence": 89,
        "average_torque": null,
        "min_torque": null,
        "max_torque": null,
        "total_elevation_gain": 5.200001,
        "min_altitude": 13.6,
        "max_altitude": 24.6,
        "average_gradient": -0.0051761367,
        "average_smo2": null,
        "average_thb": null,
        "average_smo2_2": null,
        "average_thb_2": null,
        "average_lactate": null,
        "min_lactate": null,
        "max_lactate": null,
        "average_temp": 24.215874,
        "average_weather_temp": null,
        "average_feels_like": null,
        "average_wind_speed": null,
        "average_wind_gust": null,
        "prevailing_wind_deg": null,
        "average_yaw": null,
        "headwind_percent": null,
        "tailwind_percent": null,
        "strain_score": null,
        "ss_p_max": null,
        "ss_w_prime": null,
        "ss_cp": null,
        "id": 9204025,
        "type": "WORK",
        "end_index": 315,
        "group_id": "324s@152bpm84rpm",
        "segment_effort_ids": null,
        "start_time": 0,
        "end_time": 315,
        "label": null,
        "average_stride": 1.1452461
      },
      {
        "start_index": 315,
        "distance": 1000.38,
        "moving_time": 316,
        "elapsed_time": 316,
        "average_watts": null,
        "average_watts_alt": null,
        "average_watts_alt_acc": null,
        "min_watts": null,
        "max_watts": null,
        "average_watts_kg": null,
        "max_watts_kg": null,
        "intensity": 84,
        "w5s_variability": null,
        "weighted_average_watts": null,
        "training_load": null,
        "joules": null,
        "joules_above_ftp": null,
        "decoupling": null,
        "avg_lr_balance": null,
        "average_dfa_a1": null,
        "average_epoc": null,
        "wbal_start": null,
        "wbal_end": null,
        "average_respiration": null,
        "average_tidal_volume": null,
        "average_tidal_volume_min": null,
        "zone": 1,
        "zone_min_watts": null,
        "zone_max_watts": null,
        "average_speed": 3.1657596,
        "min_speed": 2.799,
        "max_speed": 3.518,
        "gap": 3.0413215,
        "average_heartrate": 147,
        "min_heartrate": 140,
        "max_heartrate": 154,
        "average_cadence": 84.775314,
        "min_cadence": 81,
        "max_cadence": 87,
        "average_torque": null,
        "min_torque": null,
        "max_torque": null,
        "total_elevation_gain": 0.0,
        "min_altitude": 5.0,
        "max_altitude": 15.6,
        "average_gradient": -0.009596353,
        "average_smo2": null,
        "average_thb": null,
        "average_smo2_2": null,
        "average_thb_2": null,
        "average_lactate": null,
        "min_lactate": null,
        "max_lactate": null,
        "average_temp": 22.231012,
        "average_weather_temp": null,
        "average_feels_like": null,
        "average_wind_speed": null,
        "average_wind_gust": null,
        "prevailing_wind_deg": null,
        "average_yaw": null,
        "headwind_percent": null,
        "tailwind_percent": null,
        "strain_score": null,
        "ss_p_max": null,
        "ss_w_prime": null,
        "ss_cp": null,
        "id": 9264113,
        "type": "WORK",
        "end_index": 631,
        "group_id": "324s@152bpm84rpm",
        "segment_effort_ids": null,
        "start_time": 315,
        "end_time": 631,
        "label": null,
        "average_stride": 1.1202881
      },
      {
        "start_index": 631,
        "distance": 1000.54004,
        "moving_time": 332,
        "elapsed_time": 332,
        "average_watts": null,
        "average_watts_alt": null,
        "average_watts_alt_acc": null,
        "min_watts": null,
        "max_watts": null,
        "average_watts_kg": null,
        "max_watts_kg": null,
        "intensity": 84,
        "w5s_variability": null,
        "weighted_average_watts": null,
        "training_load": null,
        "joules": null,
        "joules_above_ftp": null,
        "decoupling": null,
        "avg_lr_balance": null,
        "average_dfa_a1": null,
        "average_epoc": null,
        "wbal_start": null,
        "wbal_end": null,
        "average_respiration": null,
        "average_tidal_volume": null,
        "average_tidal_volume_min": null,
        "zone": 1,
        "zone_min_watts": null,
        "zone_max_watts": null,
        "average_speed": 3.0136747,
        "min_speed": 2.734,
        "max_speed": 3.172,
        "gap": 3.1776102,
        "average_heartrate": 147,
        "min_heartrate": 137,
        "max_heartrate": 160,
        "average_cadence": 83.83132,
        "min_cadence": 79,
        "max_cadence": 86,
        "average_torque": null,
        "min_torque": null,
        "max_torque": null,
        "total_elevation_gain": 8.200001,
        "min_altitude": 5.6,
        "max_altitude": 13.6,
        "average_gradient": 0.0031982725,
        "average_smo2": null,
        "average_thb": null,
        "average_smo2_2": null,
        "average_thb_2": null,
        "average_lactate": null,
        "min_lactate": null,
        "max_lactate": null,
        "average_temp": 21.451807,
        "average_weather_temp": null,
        "average_feels_like": null,
        "average_wind_speed": null,
        "average_wind_gust": null,
        "prevailing_wind_deg": null,
        "average_yaw": null,
        "headwind_percent": null,
        "tailwind_percent": null,
        "strain_score": null,
        "ss_p_max": null,
        "ss_w_prime": null,
        "ss_cp": null,
        "id": 6404404,
        "type": "WORK",
        "end_index": 963,
        "group_id": "324s@152bpm84rpm",
        "segment_effort_ids": null,
        "start_time": 631,
        "end_time": 963,
        "label": null,
        "average_stride": 1.0784781
      },
      {
        "start_index": 963,
        "distance": 999.6499,
        "moving_time": 325,
        "elapsed_time": 325,
        "average_watts": null,
        "average_watts_alt": null,
        "average_watts_alt_acc": null,
        "min_watts": null,
        "max_watts": null,
        "average_watts_kg": null,
        "max_watts_kg": null,
        "intensity": 86,
        "w5s_variability": null,
        "weighted_average_watts": null,
        "training_load": null,
        "joules": null,
        "joules_above_ftp": null,
        "decoupling": null,
        "avg_lr_balance": null,
        "average_dfa_a1": null,
        "average_epoc": null,
        "wbal_start": null,
        "wbal_end": null,
        "average_respiration": null,
        "average_tidal_volume": null,
        "average_tidal_volume_min": null,
        "zone": 2,
        "zone_min_watts": null,
        "zone_max_watts": null,
        "average_speed": 3.075846,
        "min_speed": 2.725,
        "max_speed": 3.294,
        "gap": 3.1986446,
        "average_heartrate": 152,
        "min_heartrate": 140,
        "max_heartrate": 169,
        "average_cadence": 83.80615,
        "min_cadence": 80,
        "max_cadence": 87,
        "average_torque": null,
        "min_torque": null,
        "max_torque": null,
        "total_elevation_gain": 13.800001,
        "min_altitude": 6.4,
        "max_altitude": 16.8,
        "average_gradient": 0.0072025224,
        "average_smo2": null,
        "average_thb": null,
        "average_smo2_2": null,
        "average_thb_2": null,
        "average_lactate": null,
        "min_lactate": null,
        "max_lactate": null,
        "average_temp": 20.96,
        "average_weather_temp": null,
        "average_feels_like": null,
        "average_wind_speed": null,
        "average_wind_gust": null,
        "prevailing_wind_deg": null,
        "average_yaw": null,
        "headwind_percent": null,
        "tailwind_percent": null,
        "strain_score": null,
        "ss_p_max": null,
        "ss_w_prime": null,
        "ss_cp": null,
        "id": 2447654,
        "type": "WORK",
        "end_index": 1288,
        "group_id": "324s@152bpm84rpm",
        "segment_effort_ids": null,
        "start_time": 963,
        "end_time": 1288,
        "label": null,
        "average_stride": 1.1010573
      },
      {
        "start_index": 1288,
        "distance": 1003.8103,
        "moving_time": 325,
        "elapsed_time": 325,
        "average_watts": null,
        "average_watts_alt": null,
        "average_watts_alt_acc": null,
        "min_watts": null,
        "max_watts": null,
        "average_watts_kg": null,
        "max_watts_kg": null,
        "intensity": 85,
        "w5s_variability": null,
        "weighted_average_watts": null,
        "training_load": null,
        "joules": null,
        "joules_above_ftp": null,
        "decoupling": null,
        "avg_lr_balance": null,
        "average_dfa_a1": null,
        "average_epoc": null,
        "wbal_start": null,
        "wbal_end": null,
        "average_respiration": null,
        "average_tidal_volume": null,
        "average_tidal_volume_min": null,
        "zone": 2,
        "zone_min_watts": null,
        "zone_max_watts": null,
        "average_speed": 3.0886471,
        "min_speed": 2.967,
        "max_speed": 3.228,
        "gap": 3.0657709,
        "average_heartrate": 149,
        "min_heartrate": 137,
        "max_heartrate": 164,
        "average_cadence": 84.332306,
        "min_cadence": 81,
        "max_cadence": 88,
        "average_torque": null,
        "min_torque": null,
        "max_torque": null,
        "total_elevation_gain": 6.4000015,
        "min_altitude": 13.8,
        "max_altitude": 20.6,
        "average_gradient": -0.0023908906,
        "average_smo2": null,
        "average_thb": null,
        "average_smo2_2": null,
        "average_thb_2": null,
        "average_lactate": null,
        "min_lactate": null,
        "max_lactate": null,
        "average_temp": 21.744616,
        "average_weather_temp": null,
        "average_feels_like": null,
        "average_wind_speed": null,
        "average_wind_gust": null,
        "prevailing_wind_deg": null,
        "average_yaw": null,
        "headwind_percent": null,
        "tailwind_percent": null,
        "strain_score": null,
        "ss_p_max": null,
        "ss_w_prime": null,
        "ss_cp": null,
        "id": 6286430,
        "type": "WORK",
        "end_index": 1613,
        "group_id": "324s@152bpm84rpm",
        "segment_effort_ids": null,
        "start_time": 1288,
        "end_time": 1613,
        "label": null,
        "average_stride": 1.0987417
      },
      {
        "start_index": 1613,
        "distance": 998.23,
        "moving_time": 325,
        "elapsed_time": 401,
        "average_watts": null,
        "average_watts_alt": null,
        "average_watts_alt_acc": null,
        "min_watts": null,
        "max_watts": null,
        "average_watts_kg": null,
        "max_watts_kg": null,
        "intensity": 78,
        "w5s_variability": null,
        "weighted_average_watts": null,
        "training_load": null,
        "joules": null,
        "joules_above_ftp": null,
        "decoupling": null,
        "avg_lr_balance": null,
        "average_dfa_a1": null,
        "average_epoc": null,
        "wbal_start": null,
        "wbal_end": null,
        "average_respiration": null,
        "average_tidal_volume": null,
        "average_tidal_volume_min": null,
        "zone": 1,
        "zone_min_watts": null,
        "zone_max_watts": null,
        "average_speed": 3.071477,
        "min_speed": 0.0,
        "max_speed": 3.434,
        "gap": 3.007576,
        "average_heartrate": 137,
        "min_heartrate": 108,
        "max_heartrate": 160,
        "average_cadence": 81.88991,
        "min_cadence": 0,
        "max_cadence": 87,
        "average_torque": null,
        "min_torque": null,
        "max_torque": null,
        "total_elevation_gain": 9.400002,
        "min_altitude": 9.8,
        "max_altitude": 20.0,
        "average_gradient": -0.0044078017,
        "average_smo2": null,
        "average_thb": null,
        "average_smo2_2": null,
        "average_thb_2": null,
        "average_lactate": null,
        "min_lactate": null,
        "max_lactate": null,
        "average_temp": 22.409786,
        "average_weather_temp": null,
        "average_feels_like": null,
        "average_wind_speed": null,
        "average_wind_gust": null,
        "prevailing_wind_deg": null,
        "average_yaw": null,
        "headwind_percent": null,
        "tailwind_percent": null,
        "strain_score": null,
        "ss_p_max": null,
        "ss_w_prime": null,
        "ss_cp": null,
        "id": 2861101,
        "type": "WORK",
        "end_index": 1940,
        "group_id": "390s@139bpm81rpm",
        "segment_effort_ids": null,
        "start_time": 1613,
        "end_time": 2014,
        "label": null,
        "average_stride": 1.1252217
      },
      {
        "start_index": 1940,
        "distance": 997.75977,
        "moving_time": 321,
        "elapsed_time": 321,
        "average_watts": null,
        "average_watts_alt": null,
        "average_watts_alt_acc": null,
        "min_watts": null,
        "max_watts": null,
        "average_watts_kg": null,
        "max_watts_kg": null,
        "intensity": 84,
        "w5s_variability": null,
        "weighted_average_watts": null,
        "training_load": null,
        "joules": null,
        "joules_above_ftp": null,
        "decoupling": null,
        "avg_lr_balance": null,
        "average_dfa_a1": null,
        "average_epoc": null,
        "wbal_start": null,
        "wbal_end": null,
        "average_respiration": null,
        "average_tidal_volume": null,
        "average_tidal_volume_min": null,
        "zone": 1,
        "zone_min_watts": null,
        "zone_max_watts": null,
        "average_speed": 3.108286,
        "min_speed": 2.948,
        "max_speed": 3.284,
        "gap": 3.04145,
        "average_heartrate": 147,
        "min_heartrate": 119,
        "max_heartrate": 156,
        "average_cadence": 84.0623,
        "min_cadence": 80,
        "max_cadence": 87,
        "average_torque": null,
        "min_torque": null,
        "max_torque": null,
        "total_elevation_gain": 6.600001,
        "min_altitude": 4.2,
        "max_altitude": 10.2,
        "average_gradient": -0.0004008987,
        "average_smo2": null,
        "average_thb": null,
        "average_smo2_2": null,
        "average_thb_2": null,
        "average_lactate": null,
        "min_lactate": null,
        "max_lactate": null,
        "average_temp": 22.63863,
        "average_weather_temp": null,
        "average_feels_like": null,
        "average_wind_speed": null,
        "average_wind_gust": null,
        "prevailing_wind_deg": null,
        "average_yaw": null,
        "headwind_percent": null,
        "tailwind_percent": null,
        "strain_score": null,
        "ss_p_max": null,
        "ss_w_prime": null,
        "ss_cp": null,
        "id": 1479701,
        "type": "WORK",
        "end_index": 2261,
        "group_id": "324s@152bpm84rpm",
        "segment_effort_ids": null,
        "start_time": 2014,
        "end_time": 2335,
        "label": null,
        "average_stride": 1.1092793
      },
      {
        "start_index": 2261,
        "distance": 1001.6001,
        "moving_time": 330,
        "elapsed_time": 331,
        "average_watts": null,
        "average_watts_alt": null,
        "average_watts_alt_acc": null,
        "min_watts": null,
        "max_watts": null,
        "average_watts_kg": null,
        "max_watts_kg": null,
        "intensity": 94,
        "w5s_variability": null,
        "weighted_average_watts": null,
        "training_load": null,
        "joules": null,
        "joules_above_ftp": null,
        "decoupling": null,
        "avg_lr_balance": null,
        "average_dfa_a1": null,
        "average_epoc": null,
        "wbal_start": null,
        "wbal_end": null,
        "average_respiration": null,
        "average_tidal_volume": null,
        "average_tidal_volume_min": null,
        "zone": 3,
        "zone_min_watts": null,
        "zone_max_watts": null,
        "average_speed": 3.0351517,
        "min_speed": 2.809,
        "max_speed": 3.191,
        "gap": 3.1764147,
        "average_heartrate": 165,
        "min_heartrate": 153,
        "max_heartrate": 173,
        "average_cadence": 83.78248,
        "min_cadence": 82,
        "max_cadence": 88,
        "average_torque": null,
        "min_torque": null,
        "max_torque": null,
        "total_elevation_gain": 10.8,
        "min_altitude": 9.0,
        "max_altitude": 17.0,
        "average_gradient": 0.0037939295,
        "average_smo2": null,
        "average_thb": null,
        "average_smo2_2": null,
        "average_thb_2": null,
        "average_lactate": null,
        "min_lactate": null,
        "max_lactate": null,
        "average_temp": 21.87009,
        "average_weather_temp": null,
        "average_feels_like": null,
        "average_wind_speed": null,
        "average_wind_gust": null,
        "prevailing_wind_deg": null,
        "average_yaw": null,
        "headwind_percent": null,
        "tailwind_percent": null,
        "strain_score": null,
        "ss_p_max": null,
        "ss_w_prime": null,
        "ss_cp": null,
        "id": 8693965,
        "type": "WORK",
        "end_index": 2592,
        "group_id": "324s@152bpm84rpm",
        "segment_effort_ids": null,
        "start_time": 2335,
        "end_time": 2666,
        "label": null,
        "average_stride": 1.0867971
      },
      {
        "start_index": 2592,
        "distance": 998.5801,
        "moving_time": 324,
        "elapsed_time": 324,
        "average_watts": null,
        "average_watts_alt": null,
        "average_watts_alt_acc": null,
        "min_watts": null,
        "max_watts": null,
        "average_watts_kg": null,
        "max_watts_kg": null,
        "intensity": 94,
        "w5s_variability": null,
        "weighted_average_watts": null,
        "training_load": null,
        "joules": null,
        "joules_above_ftp": null,
        "decoupling": null,
        "avg_lr_balance": null,
        "average_dfa_a1": null,
        "average_epoc": null,
        "wbal_start": null,
        "wbal_end": null,
        "average_respiration": null,
        "average_tidal_volume": null,
        "average_tidal_volume_min": null,
        "zone": 4,
        "zone_min_watts": null,
        "zone_max_watts": null,
        "average_speed": 3.0820372,
        "min_speed": 2.753,
        "max_speed": 3.34,
        "gap": 3.189112,
        "average_heartrate": 166,
        "min_heartrate": 159,
        "max_heartrate": 173,
        "average_cadence": 83.65741,
        "min_cadence": 80,
        "max_cadence": 86,
        "average_torque": null,
        "min_torque": null,
        "max_torque": null,
        "total_elevation_gain": 16.2,
        "min_altitude": 11.6,
        "max_altitude": 29.2,
        "average_gradient": 0.014821045,
        "average_smo2": null,
        "average_thb": null,
        "average_smo2_2": null,
        "average_thb_2": null,
        "average_lactate": null,
        "min_lactate": null,
        "max_lactate": null,
        "average_temp": 22.598766,
        "average_weather_temp": null,
        "average_feels_like": null,
        "average_wind_speed": null,
        "average_wind_gust": null,
        "prevailing_wind_deg": null,
        "average_yaw": null,
        "headwind_percent": null,
        "tailwind_percent": null,
        "strain_score": null,
        "ss_p_max": null,
        "ss_w_prime": null,
        "ss_cp": null,
        "id": 4274448,
        "type": "WORK",
        "end_index": 2916,
        "group_id": "324s@152bpm84rpm",
        "segment_effort_ids": null,
        "start_time": 2666,
        "end_time": 2990,
        "label": null,
        "average_stride": 1.1052352
      },
      {
        "start_index": 2916,
        "distance": 1003.2197,
        "moving_time": 314,
        "elapsed_time": 314,
        "average_watts": null,
        "average_watts_alt": null,
        "average_watts_alt_acc": null,
        "min_watts": null,
        "max_watts": null,
        "average_watts_kg": null,
        "max_watts_kg": null,
        "intensity": 94,
        "w5s_variability": null,
        "weighted_average_watts": null,
        "training_load": null,
        "joules": null,
        "joules_above_ftp": null,
        "decoupling": null,
        "avg_lr_balance": null,
        "average_dfa_a1": null,
        "average_epoc": null,
        "wbal_start": null,
        "wbal_end": null,
        "average_respiration": null,
        "average_tidal_volume": null,
        "average_tidal_volume_min": null,
        "zone": 3,
        "zone_min_watts": null,
        "zone_max_watts": null,
        "average_speed": 3.1949673,
        "min_speed": 2.976,
        "max_speed": 3.415,
        "gap": 3.136629,
        "average_heartrate": 165,
        "min_heartrate": 153,
        "max_heartrate": 171,
        "average_cadence": 84.09554,
        "min_cadence": 81,
        "max_cadence": 88,
        "average_torque": null,
        "min_torque": null,
        "max_torque": null,
        "total_elevation_gain": 7.6000023,
        "min_altitude": 24.0,
        "max_altitude": 36.6,
        "average_gradient": -0.0035884446,
        "average_smo2": null,
        "average_thb": null,
        "average_smo2_2": null,
        "average_thb_2": null,
        "average_lactate": null,
        "min_lactate": null,
        "max_lactate": null,
        "average_temp": 23.003185,
        "average_weather_temp": null,
        "average_feels_like": null,
        "average_wind_speed": null,
        "average_wind_gust": null,
        "prevailing_wind_deg": null,
        "average_yaw": null,
        "headwind_percent": null,
        "tailwind_percent": null,
        "strain_score": null,
        "ss_p_max": null,
        "ss_w_prime": null,
        "ss_cp": null,
        "id": 9073124,
        "type": "WORK",
        "end_index": 3230,
        "group_id": "324s@152bpm84rpm",
        "segment_effort_ids": null,
        "start_time": 2990,
        "end_time": 3304,
        "label": null,
        "average_stride": 1.1397634
      },
      {
        "start_index": 3230,
        "distance": 996.2002,
        "moving_time": 339,
        "elapsed_time": 779,
        "average_watts": null,
        "average_watts_alt": null,
        "average_watts_alt_acc": null,
        "min_watts": null,
        "max_watts": null,
        "average_watts_kg": null,
        "max_watts_kg": null,
        "intensity": 72,
        "w5s_variability": null,
        "weighted_average_watts": null,
        "training_load": null,
        "joules": null,
        "joules_above_ftp": null,
        "decoupling": null,
        "avg_lr_balance": null,
        "average_dfa_a1": null,
        "average_epoc": null,
        "wbal_start": null,
        "wbal_end": null,
        "average_respiration": null,
        "average_tidal_volume": null,
        "average_tidal_volume_min": null,
        "zone": 1,
        "zone_min_watts": null,
        "zone_max_watts": null,
        "average_speed": 2.9386437,
        "min_speed": 0.0,
        "max_speed": 3.499,
        "gap": 2.8061202,
        "average_heartrate": 126,
        "min_heartrate": 87,
        "max_heartrate": 164,
        "average_cadence": 81.31672,
        "min_cadence": 0,
        "max_cadence": 88,
        "average_torque": null,
        "min_torque": null,
        "max_torque": null,
        "total_elevation_gain": 2.6000004,
        "min_altitude": 15.2,
        "max_altitude": 26.4,
        "average_gradient": -0.008432041,
        "average_smo2": null,
        "average_thb": null,
        "average_smo2_2": null,
        "average_thb_2": null,
        "average_lactate": null,
        "min_lactate": null,
        "max_lactate": null,
        "average_temp": 24.630499,
        "average_weather_temp": null,
        "average_feels_like": null,
        "average_wind_speed": null,
        "average_wind_gust": null,
        "prevailing_wind_deg": null,
        "average_yaw": null,
        "headwind_percent": null,
        "tailwind_percent": null,
        "strain_score": null,
        "ss_p_max": null,
        "ss_w_prime": null,
        "ss_cp": null,
        "id": 5441074,
        "type": "WORK",
        "end_index": 3571,
        "group_id": "779s@126bpm81rpm",
        "segment_effort_ids": null,
        "start_time": 3304,
        "end_time": 4083,
        "label": null,
        "average_stride": 1.0841475
      },
      {
        "start_index": 3571,
        "distance": 1002.6699,
        "moving_time": 329,
        "elapsed_time": 379,
        "average_watts": null,
        "average_watts_alt": null,
        "average_watts_alt_acc": null,
        "min_watts": null,
        "max_watts": null,
        "average_watts_kg": null,
        "max_watts_kg": null,
        "intensity": 80,
        "w5s_variability": null,
        "weighted_average_watts": null,
        "training_load": null,
        "joules": null,
        "joules_above_ftp": null,
        "decoupling": null,
        "avg_lr_balance": null,
        "average_dfa_a1": null,
        "average_epoc": null,
        "wbal_start": null,
        "wbal_end": null,
        "average_respiration": null,
        "average_tidal_volume": null,
        "average_tidal_volume_min": null,
        "zone": 1,
        "zone_min_watts": null,
        "zone_max_watts": null,
        "average_speed": 3.0476289,
        "min_speed": 0.0,
        "max_speed": 3.49,
        "gap": 3.0312965,
        "average_heartrate": 140,
        "min_heartrate": 126,
        "max_heartrate": 152,
        "average_cadence": 79.749245,
        "min_cadence": 0,
        "max_cadence": 87,
        "average_torque": null,
        "min_torque": null,
        "max_torque": null,
        "total_elevation_gain": 3.8000011,
        "min_altitude": 10.2,
        "max_altitude": 16.4,
        "average_gradient": -0.005585089,
        "average_smo2": null,
        "average_thb": null,
        "average_smo2_2": null,
        "average_thb_2": null,
        "average_lactate": null,
        "min_lactate": null,
        "max_lactate": null,
        "average_temp": 23.546827,
        "average_weather_temp": null,
        "average_feels_like": null,
        "average_wind_speed": null,
        "average_wind_gust": null,
        "prevailing_wind_deg": null,
        "average_yaw": null,
        "headwind_percent": null,
        "tailwind_percent": null,
        "strain_score": null,
        "ss_p_max": null,
        "ss_w_prime": null,
        "ss_cp": null,
        "id": 4088746,
        "type": "WORK",
        "end_index": 3902,
        "group_id": "390s@139bpm81rpm",
        "segment_effort_ids": null,
        "start_time": 4083,
        "end_time": 4462,
        "label": null,
        "average_stride": 1.1464543
      },
      {
        "start_index": 3902,
        "distance": 998.48047,
        "moving_time": 335,
        "elapsed_time": 335,
        "average_watts": null,
        "average_watts_alt": null,
        "average_watts_alt_acc": null,
        "min_watts": null,
        "max_watts": null,
        "average_watts_kg": null,
        "max_watts_kg": null,
        "intensity": 83,
        "w5s_variability": null,
        "weighted_average_watts": null,
        "training_load": null,
        "joules": null,
        "joules_above_ftp": null,
        "decoupling": null,
        "avg_lr_balance": null,
        "average_dfa_a1": null,
        "average_epoc": null,
        "wbal_start": null,
        "wbal_end": null,
        "average_respiration": null,
        "average_tidal_volume": null,
        "average_tidal_volume_min": null,
        "zone": 1,
        "zone_min_watts": null,
        "zone_max_watts": null,
        "average_speed": 2.9805386,
        "min_speed": 2.846,
        "max_speed": 3.144,
        "gap": 2.910418,
        "average_heartrate": 146,
        "min_heartrate": 137,
        "max_heartrate": 152,
        "average_cadence": 83.414925,
        "min_cadence": 0,
        "max_cadence": 86,
        "average_torque": null,
        "min_torque": null,
        "max_torque": null,
        "total_elevation_gain": 8.000001,
        "min_altitude": 7.8,
        "max_altitude": 16.8,
        "average_gradient": -0.0010015218,
        "average_smo2": null,
        "average_thb": null,
        "average_smo2_2": null,
        "average_thb_2": null,
        "average_lactate": null,
        "min_lactate": null,
        "max_lactate": null,
        "average_temp": 22.979105,
        "average_weather_temp": null,
        "average_feels_like": null,
        "average_wind_speed": null,
        "average_wind_gust": null,
        "prevailing_wind_deg": null,
        "average_yaw": null,
        "headwind_percent": null,
        "tailwind_percent": null,
        "strain_score": null,
        "ss_p_max": null,
        "ss_w_prime": null,
        "ss_cp": null,
        "id": 7189434,
        "type": "WORK",
        "end_index": 4237,
        "group_id": "324s@152bpm84rpm",
        "segment_effort_ids": null,
        "start_time": 4462,
        "end_time": 4797,
        "label": null,
        "average_stride": 1.0719444
      },
      {
        "start_index": 4237,
        "distance": 1002.0,
        "moving_time": 323,
        "elapsed_time": 323,
        "average_watts": null,
        "average_watts_alt": null,
        "average_watts_alt_acc": null,
        "min_watts": null,
        "max_watts": null,
        "average_watts_kg": null,
        "max_watts_kg": null,
        "intensity": 82,
        "w5s_variability": null,
        "weighted_average_watts": null,
        "training_load": null,
        "joules": null,
        "joules_above_ftp": null,
        "decoupling": null,
        "avg_lr_balance": null,
        "average_dfa_a1": null,
        "average_epoc": null,
        "wbal_start": null,
        "wbal_end": null,
        "average_respiration": null,
        "average_tidal_volume": null,
        "average_tidal_volume_min": null,
        "zone": 1,
        "zone_min_watts": null,
        "zone_max_watts": null,
        "average_speed": 3.1021671,
        "min_speed": 2.874,
        "max_speed": 3.266,
        "gap": 3.1820672,
        "average_heartrate": 144,
        "min_heartrate": 141,
        "max_heartrate": 147,
        "average_cadence": 84.572754,
        "min_cadence": 82,
        "max_cadence": 87,
        "average_torque": null,
        "min_torque": null,
        "max_torque": null,
        "total_elevation_gain": 8.6,
        "min_altitude": 9.0,
        "max_altitude": 15.2,
        "average_gradient": 0.005788423,
        "average_smo2": null,
        "average_thb": null,
        "average_smo2_2": null,
        "average_thb_2": null,
        "average_lactate": null,
        "min_lactate": null,
        "max_lactate": null,
        "average_temp": 22.582043,
        "average_weather_temp": null,
        "average_feels_like": null,
        "average_wind_speed": null,
        "average_wind_gust": null,
        "prevailing_wind_deg": null,
        "average_yaw": null,
        "headwind_percent": null,
        "tailwind_percent": null,
        "strain_score": null,
        "ss_p_max": null,
        "ss_w_prime": null,
        "ss_cp": null,
        "id": 2947192,
        "type": "WORK",
        "end_index": 4560,
        "group_id": "324s@152bpm84rpm",
        "segment_effort_ids": null,
        "start_time": 4797,
        "end_time": 5120,
        "label": null,
        "average_stride": 1.1004137
      },
      {
        "start_index": 4560,
        "distance": 999.11914,
        "moving_time": 324,
        "elapsed_time": 324,
        "average_watts": null,
        "average_watts_alt": null,
        "average_watts_alt_acc": null,
        "min_watts": null,
        "max_watts": null,
        "average_watts_kg": null,
        "max_watts_kg": null,
        "intensity": 86,
        "w5s_variability": null,
        "weighted_average_watts": null,
        "training_load": null,
        "joules": null,
        "joules_above_ftp": null,
        "decoupling": null,
        "avg_lr_balance": null,
        "average_dfa_a1": null,
        "average_epoc": null,
        "wbal_start": null,
        "wbal_end": null,
        "average_respiration": null,
        "average_tidal_volume": null,
        "average_tidal_volume_min": null,
        "zone": 2,
        "zone_min_watts": null,
        "zone_max_watts": null,
        "average_speed": 3.0837011,
        "min_speed": 2.976,
        "max_speed": 3.228,
        "gap": 3.1731303,
        "average_heartrate": 151,
        "min_heartrate": 143,
        "max_heartrate": 162,
        "average_cadence": 83.611115,
        "min_cadence": 43,
        "max_cadence": 88,
        "average_torque": null,
        "min_torque": null,
        "max_torque": null,
        "total_elevation_gain": 10.8,
        "min_altitude": 14.4,
        "max_altitude": 25.6,
        "average_gradient": 0.010809522,
        "average_smo2": null,
        "average_thb": null,
        "average_smo2_2": null,
        "average_thb_2": null,
        "average_lactate": null,
        "min_lactate": null,
        "max_lactate": null,
        "average_temp": 22.02469,
        "average_weather_temp": null,
        "average_feels_like": null,
        "average_wind_speed": null,
        "average_wind_gust": null,
        "prevailing_wind_deg": null,
        "average_yaw": null,
        "headwind_percent": null,
        "tailwind_percent": null,
        "strain_score": null,
        "ss_p_max": null,
        "ss_w_prime": null,
        "ss_cp": null,
        "id": 9986867,
        "type": "WORK",
        "end_index": 4884,
        "group_id": "324s@152bpm84rpm",
        "segment_effort_ids": null,
        "start_time": 5120,
        "end_time": 5444,
        "label": null,
        "average_stride": 1.1064441
      },
      {
        "start_index": 4884,
        "distance": 572.98047,
        "moving_time": 180,
        "elapsed_time": 192,
        "average_watts": null,
        "average_watts_alt": null,
        "average_watts_alt_acc": null,
        "min_watts": null,
        "max_watts": null,
        "average_watts_kg": null,
        "max_watts_kg": null,
        "intensity": 87,
        "w5s_variability": null,
        "weighted_average_watts": null,
        "training_load": null,
        "joules": null,
        "joules_above_ftp": null,
        "decoupling": null,
        "avg_lr_balance": null,
        "average_dfa_a1": null,
        "average_epoc": null,
        "wbal_start": null,
        "wbal_end": null,
        "average_respiration": null,
        "average_tidal_volume": null,
        "average_tidal_volume_min": null,
        "zone": 2,
        "zone_min_watts": null,
        "zone_max_watts": null,
        "average_speed": 3.183225,
        "min_speed": 0.0,
        "max_speed": 3.583,
        "gap": 3.170712,
        "average_heartrate": 153,
        "min_heartrate": 148,
        "max_heartrate": 162,
        "average_cadence": 82.65193,
        "min_cadence": 0,
        "max_cadence": 87,
        "average_torque": null,
        "min_torque": null,
        "max_torque": null,
        "total_elevation_gain": 0.0,
        "min_altitude": 22.6,
        "max_altitude": 26.6,
        "average_gradient": -0.0048867306,
        "average_smo2": null,
        "average_thb": null,
        "average_smo2_2": null,
        "average_thb_2": null,
        "average_lactate": null,
        "min_lactate": null,
        "max_lactate": null,
        "average_temp": 22.983425,
        "average_weather_temp": null,
        "average_feels_like": null,
        "average_wind_speed": null,
        "average_wind_gust": null,
        "prevailing_wind_deg": null,
        "average_yaw": null,
        "headwind_percent": null,
        "tailwind_percent": null,
        "strain_score": null,
        "ss_p_max": null,
        "ss_w_prime": null,
        "ss_cp": null,
        "id": 8919194,
        "type": "WORK",
        "end_index": 5065,
        "group_id": "192s@153bpm83rpm",
        "segment_effort_ids": null,
        "start_time": 5444,
        "end_time": 5636,
        "label": null,
        "average_stride": 1.1554084
      }
    ],
    "icu_groups": [
      {
        "start_index": 0,
        "distance": 1000.81244,
        "moving_time": 324,
        "elapsed_time": 324,
        "average_watts": null,
        "average_watts_alt": null,
        "average_watts_alt_acc": null,
        "min_watts": null,
        "max_watts": null,
        "average_watts_kg": null,
        "max_watts_kg": null,
        "intensity": null,
        "w5s_variability": null,
        "weighted_average_watts": null,
        "training_load": null,
        "joules": null,
        "joules_above_ftp": null,
        "decoupling": null,
        "avg_lr_balance": null,
        "average_dfa_a1": null,
        "average_epoc": null,
        "wbal_start": null,
        "wbal_end": null,
        "average_respiration": null,
        "average_tidal_volume": null,
        "average_tidal_volume_min": null,
        "zone": 2,
        "zone_min_watts": null,
        "zone_max_watts": null,
        "average_speed": 3.0933344,
        "min_speed": 0.0,
        "max_speed": 4.264,
        "gap": 3.115232,
        "average_heartrate": 152,
        "min_heartrate": 83,
        "max_heartrate": 173,
        "average_cadence": 84.0,
        "min_cadence": 0,
        "max_cadence": 89,
        "average_torque": null,
        "min_torque": null,
        "max_torque": null,
        "total_elevation_gain": 8.516667,
        "min_altitude": null,
        "max_altitude": null,
        "average_gradient": null,
        "average_smo2": null,
        "average_thb": null,
        "average_smo2_2": null,
        "average_thb_2": null,
        "average_lactate": null,
        "min_lactate": null,
        "max_lactate": null,
        "average_temp": null,
        "average_weather_temp": null,
        "average_feels_like": null,
        "average_wind_speed": null,
        "average_wind_gust": null,
        "prevailing_wind_deg": null,
        "average_yaw": null,
        "headwind_percent": null,
        "tailwind_percent": null,
        "strain_score": null,
        "ss_p_max": null,
        "ss_w_prime": null,
        "ss_cp": null,
        "id": "324s@152bpm84rpm",
        "count": 12,
        "average_stride": 1.1031883
      },
      {
        "start_index": 1613,
        "distance": 1000.44995,
        "moving_time": 327,
        "elapsed_time": 390,
        "average_watts": null,
        "average_watts_alt": null,
        "average_watts_alt_acc": null,
        "min_watts": null,
        "max_watts": null,
        "average_watts_kg": null,
        "max_watts_kg": null,
        "intensity": null,
        "w5s_variability": null,
        "weighted_average_watts": null,
        "training_load": null,
        "joules": null,
        "joules_above_ftp": null,
        "decoupling": null,
        "avg_lr_balance": null,
        "average_dfa_a1": null,
        "average_epoc": null,
        "wbal_start": null,
        "wbal_end": null,
        "average_respiration": null,
        "average_tidal_volume": null,
        "average_tidal_volume_min": null,
        "zone": 1,
        "zone_min_watts": null,
        "zone_max_watts": null,
        "average_speed": 3.059553,
        "min_speed": 0.0,
        "max_speed": 3.49,
        "gap": 3.0194364,
        "average_heartrate": 139,
        "min_heartrate": 108,
        "max_heartrate": 160,
        "average_cadence": 81.0,
        "min_cadence": 0,
        "max_cadence": 87,
        "average_torque": null,
        "min_torque": null,
        "max_torque": null,
        "total_elevation_gain": 6.6000013,
        "min_altitude": null,
        "max_altitude": null,
        "average_gradient": null,
        "average_smo2": null,
        "average_thb": null,
        "average_smo2_2": null,
        "average_thb_2": null,
        "average_lactate": null,
        "min_lactate": null,
        "max_lactate": null,
        "average_temp": null,
        "average_weather_temp": null,
        "average_feels_like": null,
        "average_wind_speed": null,
        "average_wind_gust": null,
        "prevailing_wind_deg": null,
        "average_yaw": null,
        "headwind_percent": null,
        "tailwind_percent": null,
        "strain_score": null,
        "ss_p_max": null,
        "ss_w_prime": null,
        "ss_cp": null,
        "id": "390s@139bpm81rpm",
        "count": 2,
        "average_stride": 1.1331407
      },
      {
        "start_index": 3230,
        "distance": 996.2002,
        "moving_time": 339,
        "elapsed_time": 779,
        "average_watts": null,
        "average_watts_alt": null,
        "average_watts_alt_acc": null,
        "min_watts": null,
        "max_watts": null,
        "average_watts_kg": null,
        "max_watts_kg": null,
        "intensity": null,
        "w5s_variability": null,
        "weighted_average_watts": null,
        "training_load": null,
        "joules": null,
        "joules_above_ftp": null,
        "decoupling": null,
        "avg_lr_balance": null,
        "average_dfa_a1": null,
        "average_epoc": null,
        "wbal_start": null,
        "wbal_end": null,
        "average_respiration": null,
        "average_tidal_volume": null,
        "average_tidal_volume_min": null,
        "zone": 1,
        "zone_min_watts": null,
        "zone_max_watts": null,
        "average_speed": 2.9386437,
        "min_speed": 0.0,
        "max_speed": 3.499,
        "gap": 2.8061202,
        "average_heartrate": 126,
        "min_heartrate": 87,
        "max_heartrate": 164,
        "average_cadence": 81.0,
        "min_cadence": 0,
        "max_cadence": 88,
        "average_torque": null,
        "min_torque": null,
        "max_torque": null,
        "total_elevation_gain": 2.6000004,
        "min_altitude": null,
        "max_altitude": null,
        "average_gradient": null,
        "average_smo2": null,
        "average_thb": null,
        "average_smo2_2": null,
        "average_thb_2": null,
        "average_lactate": null,
        "min_lactate": null,
        "max_lactate": null,
        "average_temp": null,
        "average_weather_temp": null,
        "average_feels_like": null,
        "average_wind_speed": null,
        "average_wind_gust": null,
        "prevailing_wind_deg": null,
        "average_yaw": null,
        "headwind_percent": null,
        "tailwind_percent": null,
        "strain_score": null,
        "ss_p_max": null,
        "ss_w_prime": null,
        "ss_cp": null,
        "id": "779s@126bpm81rpm",
        "count": 1,
        "average_stride": 1.0883865
      },
      {
        "start_index": 4884,
        "distance": 572.98047,
        "moving_time": 180,
        "elapsed_time": 192,
        "average_watts": null,
        "average_watts_alt": null,
        "average_watts_alt_acc": null,
        "min_watts": null,
        "max_watts": null,
        "average_watts_kg": null,
        "max_watts_kg": null,
        "intensity": null,
        "w5s_variability": null,
        "weighted_average_watts": null,
        "training_load": null,
        "joules": null,
        "joules_above_ftp": null,
        "decoupling": null,
        "avg_lr_balance": null,
        "average_dfa_a1": null,
        "average_epoc": null,
        "wbal_start": null,
        "wbal_end": null,
        "average_respiration": null,
        "average_tidal_volume": null,
        "average_tidal_volume_min": null,
        "zone": 2,
        "zone_min_watts": null,
        "zone_max_watts": null,
        "average_speed": 3.183225,
        "min_speed": 0.0,
        "max_speed": 3.583,
        "gap": 3.170712,
        "average_heartrate": 153,
        "min_heartrate": 148,
        "max_heartrate": 162,
        "average_cadence": 83.0,
        "min_cadence": 0,
        "max_cadence": 87,
        "average_torque": null,
        "min_torque": null,
        "max_torque": null,
        "total_elevation_gain": null,
        "min_altitude": null,
        "max_altitude": null,
        "average_gradient": null,
        "average_smo2": null,
        "average_thb": null,
        "average_smo2_2": null,
        "average_thb_2": null,
        "average_lactate": null,
        "min_lactate": null,
        "max_lactate": null,
        "average_temp": null,
        "average_weather_temp": null,
        "average_feels_like": null,
        "average_wind_speed": null,
        "average_wind_gust": null,
        "prevailing_wind_deg": null,
        "average_yaw": null,
        "headwind_percent": null,
        "tailwind_percent": null,
        "strain_score": null,
        "ss_p_max": null,
        "ss_w_prime": null,
        "ss_cp": null,
        "id": "192s@153bpm83rpm",
        "count": 1,
        "average_stride": 1.1505632
      }
    ]
  },
  "weather": null
}